pyhue/Bridge.py
pyhue/Lights.py
pyhue/__init__.py
pyhue/libs/ColourConverter.py
pyhue/libs/__init__.py
py3_PyHue-0.2a0.dist-info/LICENSE
py3_PyHue-0.2a0.dist-info/METADATA
py3_PyHue-0.2a0.dist-info/WHEEL
py3_PyHue-0.2a0.dist-info/top_level.txt
py3_PyHue-0.2a0.dist-info/RECORD
