Metadata-Version: 2.1
Name: py3-PyHue
Version: 0.2a0
Summary: Python3 Module for controlling Philips Hue lights
Home-page: https://github.com/jkampich1411/PyHue
Author: Jakob K
Author-email: me@jkdev.run
License: MIT
Classifier: Programming Language :: Python :: 3
Requires: zeroconf
Requires: requests
License-File: LICENSE
Requires-Dist: zeroconf
Requires-Dist: requests
